manage_django_project/__init__.py
manage_django_project/apps.py
manage_django_project/config.py
manage_django_project/exceptions.py
manage_django_project/manage.py
manage_django_project/test_utilities.py
manage_django_project/management/__init__.py
manage_django_project/management/base.py
manage_django_project/management/commands/__init__.py
manage_django_project/management/commands/code_style.py
manage_django_project/management/commands/coverage.py
manage_django_project/management/commands/install.py
manage_django_project/management/commands/make_messages.py
manage_django_project/management/commands/nox.py
manage_django_project/management/commands/pip_audit.py
manage_django_project/management/commands/playwright.py
manage_django_project/management/commands/project_info.py
manage_django_project/management/commands/publish.py
manage_django_project/management/commands/run_dev_server.py
manage_django_project/management/commands/shell.py
manage_django_project/management/commands/update_req.py
manage_django_project/management/commands/update_test_snapshot_files.py
manage_django_project/static/manage_django_project.svg
manage_django_project/tests/__init__.py
manage_django_project/tests/cmd2_test_utils.py
manage_django_project/tests/command_test_utils.py
manage_django_project/tests/test_command_code_style.py
manage_django_project/tests/test_command_coverage.py
manage_django_project/tests/test_command_install.py
manage_django_project/tests/test_command_nox.py
manage_django_project/tests/test_command_pip_audit.py
manage_django_project/tests/test_command_playwright.py
manage_django_project/tests/test_command_project_info.py
manage_django_project/tests/test_command_project_info_project_info_1.snapshot.txt
manage_django_project/tests/test_command_publish.py
manage_django_project/tests/test_command_run_dev_server.py
manage_django_project/tests/test_command_run_dev_server_basic_run_dev_server_1.snapshot.txt
manage_django_project/tests/test_command_shell.py
manage_django_project-0.11.2.dist-info/METADATA
manage_django_project-0.11.2.dist-info/WHEEL
manage_django_project-0.11.2.dist-info/entry_points.txt
manage_django_project-0.11.2.dist-info/licenses/LICENSE
manage_django_project-0.11.2.dist-info/RECORD
