Metadata-Version: 2.4
Name: manage_django_project
Version: 0.11.2
Summary: Helper to develop Django projects.
Project-URL: Documentation, https://github.com/jedie/manage_django_project
Project-URL: Source, https://github.com/jedie/manage_django_project
Author-email: Jens Diemer <git@jensdiemer.de>
License: GPL-3.0-or-later
License-File: LICENSE
Requires-Python: >=3.11
Requires-Dist: bx-py-utils
Requires-Dist: cli-base-utilities>=0.17.1
Requires-Dist: cmd2
Requires-Dist: django
Requires-Dist: django-rich
Requires-Dist: django-tools>=0.57.0
Requires-Dist: manageprojects
